{"UserInfo":{"display_name":"","account":"","mod":"","uuid":"","userProperties":null,"accessToken":"","profileProperties":{"textures":"","uploadableTextures":""},"selected":false},"LauncherSettings":{"javaList":null,"gameDir":null,"config":{"global":{"useGlobal":true,"maxMemory":1024,"autoMemory":true,"javaArgs":"","java":"","defaultJavaPath":""},"private":null},"download":{"retryTimes":3,"singleThreads":4,"downloadThreads":100,"source":{"official":{"VersionList_V1":"http://launchermeta.mojang.com/mc/game/version_manifest.json","version_list___v_2":"http://launchermeta.mojang.com/mc/game/version_manifest_v2.json","index":"https://launchermeta.mojang.com/","launcher":"https://launcher.mojang.com/","assets":"http://resources.download.minecraft.net/","libraries":"https://libraries.minecraft.net/"},"BMCL":{"VersionList_V1":"https://bmclapi2.bangbang93.com/mc/game/version_manifest.json","version_list___v_2":"https://bmclapi2.bangbang93.com/mc/game/version_manifest_v2.json","index":"https://bmclapi2.bangbang93.com/","launcher":"https://bmclapi2.bangbang93.com/","assets":"https://bmclapi2.bangbang93.com/assets/","libraries":"https://bmclapi2.bangbang93.com/maven/"},"MCBBS":{"VersionList_V1":"https://download.mcbbs.net/mc/game/version_manifest.json","version_list___v_2":"https://download.mcbbs.net/mc/game/version_manifest_v2.json","index":"https://download.mcbbs.net/","launcher":"https://download.mcbbs.net/","assets":"https://download.mcbbs.net/assets/","libraries":"https://download.mcbbs.net/maven/"},"Others":{"VersionList_V1":"","version_list___v_2":"","index":"","launcher":"","assets":"","libraries":""}},"mod":2},"autoLog":true,"about":{"version":"0.1.1_Alpha","url":"https://mcskin.cn/"}}}